poglossary/__init__.py
poglossary/__main__.py
poglossary/config.py
poglossary/find_sources.py
poglossary/logger.py
poglossary/poglossary.py
poglossary-0.1.4.dist-info/entry_points.txt
poglossary-0.1.4.dist-info/LICENSE
poglossary-0.1.4.dist-info/WHEEL
poglossary-0.1.4.dist-info/METADATA
poglossary-0.1.4.dist-info/RECORD
