Metadata-Version: 2.1
Name: poglossary
Version: 0.1.4
Summary: A CLI tool that scans through .po files and searches for mistranslated terms based on user-defined glossary mapping
License: MIT
Author: Matt.Wang
Author-email: mattwang44@gmail.com
Requires-Python: >=3.9,<4.0
Classifier: License :: OSI Approved :: MIT License
Classifier: Programming Language :: Python :: 3
Classifier: Programming Language :: Python :: 3.10
Classifier: Programming Language :: Python :: 3.9
Requires-Dist: PyYAML (>=6.0,<7.0)
Requires-Dist: polib (>=1.1.1,<2.0.0)
Requires-Dist: pydantic (>=1.9.0,<2.0.0)
Requires-Dist: tabulate[widechars] (>=0.8.9,<0.9.0)
Requires-Dist: typer[all] (>=0.4.0,<0.5.0)
